notebooks_and_scripts/README.py
notebooks_and_scripts/__init__.py
notebooks_and_scripts/__main__.py
notebooks_and_scripts/config.env
notebooks_and_scripts/env.py
notebooks_and_scripts/logger.py
notebooks_and_scripts/sample.env
notebooks_and_scripts/urls.py
notebooks_and_scripts/.abcli/actions.sh
notebooks_and_scripts/.abcli/aka.sh
notebooks_and_scripts/.abcli/alias.sh
notebooks_and_scripts/.abcli/aws_batch.sh
notebooks_and_scripts/.abcli/docker.sh
notebooks_and_scripts/.abcli/huggingface.sh
notebooks_and_scripts/.abcli/jupyter-notebook.sh
notebooks_and_scripts/.abcli/meta_scripts.sh
notebooks_and_scripts/.abcli/notebooks-and-scripts.sh
notebooks_and_scripts/.abcli/sagemaker.sh
notebooks_and_scripts/.abcli/scripts.sh
notebooks_and_scripts/.abcli/workflow.sh
notebooks_and_scripts/.abcli/aws_batch/browse.sh
notebooks_and_scripts/.abcli/aws_batch/cat.sh
notebooks_and_scripts/.abcli/aws_batch/eval.sh
notebooks_and_scripts/.abcli/aws_batch/list.sh
notebooks_and_scripts/.abcli/aws_batch/submit.sh
notebooks_and_scripts/.abcli/docker/browse.sh
notebooks_and_scripts/.abcli/docker/build.sh
notebooks_and_scripts/.abcli/docker/clear.sh
notebooks_and_scripts/.abcli/docker/push.sh
notebooks_and_scripts/.abcli/docker/run.sh
notebooks_and_scripts/.abcli/docker/seed.sh
notebooks_and_scripts/.abcli/jupyter-notebook/build.sh
notebooks_and_scripts/.abcli/jupyter-notebook/code.sh
notebooks_and_scripts/.abcli/jupyter-notebook/connect.sh
notebooks_and_scripts/.abcli/jupyter-notebook/create.sh
notebooks_and_scripts/.abcli/jupyter-notebook/host.sh
notebooks_and_scripts/.abcli/jupyter-notebook/open.sh
notebooks_and_scripts/.abcli/tests/README.sh
notebooks_and_scripts/.abcli/tests/help.sh
notebooks_and_scripts/.abcli/tests/version.sh
notebooks_and_scripts/.abcli/tests/workflow_runner.sh
notebooks_and_scripts/.abcli/workflow/config.sh
notebooks_and_scripts/.abcli/workflow/create.sh
notebooks_and_scripts/.abcli/workflow/monitor.sh
notebooks_and_scripts/.abcli/workflow/submit.sh
notebooks_and_scripts-4.759.1.dist-info/LICENSE
notebooks_and_scripts-4.759.1.dist-info/METADATA
notebooks_and_scripts-4.759.1.dist-info/WHEEL
notebooks_and_scripts-4.759.1.dist-info/top_level.txt
notebooks_and_scripts-4.759.1.dist-info/RECORD
